{"name":"Material-design-css-framework","tagline":"CSS Framework following specifications of Material Design from Google.","body":"Material Design CSS Framework\r\n======\r\n\r\n¡¡Work in progress!!\r\n\r\n\r\n## Avoid CORS (same origin policy)\r\nIf you are testing Material Design CSS Framework, **same origin police** restrict you access to local file `custom_styles.html`. \r\nThe solution if you need to test it locally without a web server (on local) is disable your browser security policy temporaly. \r\nRead below to know how to disable local files security policy in common browsers.\r\n\r\n### Change local files security policy\r\n\r\n#### Safari\r\n\r\nEnable the develop menu using the preferences panel, under Advanced -> \"Show develop menu in menu bar\"\r\n\r\nThen from the safari \"Develop\" menu, select \"Disable local file restrictions\", it is also worth noting safari has some odd behaviour with caches, so it is advisable to use the \"Disable caches\" option in the same menu; if you are editing & debugging using safari.\r\n\r\n#### OSX Chrome\r\nStart Chrome executable with a command line flag:\r\n```\r\nopen -a 'Google Chrome' --args -allow-file-access-from-files\r\n```\r\n\r\n#### Unix Chrome\r\nStart Chrome from command line with flag:\r\n```\r\ngoogle-chrome  --allow-file-access-from-files\r\n```\r\n\r\n#### Windows Chrome\r\nClose all running chrome instances first. Then start Chrome executable with a command line flag:\r\n\r\n```\r\nchrome --allow-file-access-from-files\r\n```\r\n\r\nOn Windows, the easiest is probably to create a special shortcut which has added flag (right-click on shortcut -> properties -> target).\r\n\r\n#### Firefox\r\n\r\n1. Go to `about:config`\r\n2. Find `security.fileuri.strict_origin_policy` parameter\r\n3. Set it to `false`\r\n\r\n#### Internet Explorer 11\r\nTested over version 11.0.9600.16438 and shows ok.\r\n\r\n### Checking which flags are Enabled in Google Chrome\r\n\r\n####In the browser\r\nOpen new tab to the URL ‘chrome://version/’ shows common information about Google Chrome loaded environment. \r\nThe block **Command Line** should show you the list of enabled flags. (ex. `\"C:\\Program Files (x86)\\Google\\Chrome\\Application\\chrome.exe\" --allow-file-access-from-files --flag-switches-begin --flag-switches-end`)","google":"","note":"Don't delete this file! It's used internally to help with page regeneration."}